{
  "name" : "Roo.htmleditor.FilterStyleToTag",
  "augments" : [],
  "childClasses" : {  },
  "tree_children" : [],
  "tree_parent" : [],
  "desc" : "part of the word stuff... - certain 'styles' should be converted to tags.\neg.\n  font-weight: bold -> bold\n  ?? super / subscrit etc..",
  "isSingleton" : false,
  "isStatic" : false,
  "isBuiltin" : false,
  "isAbstract" : false,
  "isBuilderTop" : false,
  "memberOf" : "FilterStyleToTag",
  "example" : "",
  "deprecated" : "",
  "since" : "",
  "see" : "",
  "params" : [
    {
      "name" : "config",
      "type" : "Object",
      "desc" : "Configuration options",
      "isOptional" : false
    }
  ],
  "returns" : [],
  "throws" : "",
  "requires" : "",
  "config" : [],
  "methods" : [],
  "events" : []
}