{
  "name" : "Roo.state.Provider",
  "augments" : [],
  "childClasses" : {
    "Roo.state.Provider" : [
      "Roo.state.CookieProvider"
    ]
  },
  "tree_children" : [],
  "tree_parent" : [],
  "desc" : "Abstract base class for state provider implementations. This class provides methods\nfor encoding and decoding <b>typed</b> variables including dates and defines the \nProvider interface.",
  "isSingleton" : false,
  "isStatic" : true,
  "isBuiltin" : false,
  "isAbstract" : false,
  "isBuilderTop" : false,
  "memberOf" : "Provider",
  "example" : "",
  "deprecated" : "",
  "since" : "",
  "see" : "",
  "params" : [],
  "returns" : [],
  "throws" : "",
  "requires" : "",
  "config" : [],
  "methods" : [
    {
      "name" : "clear",
      "type" : "function",
      "desc" : "Clears a value from the state",
      "sig" : "(name)",
      "static" : false,
      "memberOf" : "",
      "isStatic" : false,
      "isConstructor" : false,
      "isPrivate" : false,
      "example" : "",
      "deprecated" : "",
      "since" : "",
      "see" : "",
      "exceptions" : "",
      "requires" : "",
      "params" : [
        {
          "name" : "name",
          "type" : "String",
          "desc" : "The key name",
          "isOptional" : false
        }
      ],
      "returns" : []
    },
    {
      "name" : "decodeValue",
      "type" : "function",
      "desc" : "Decodes a string previously encoded with {@link #encodeValue}.",
      "sig" : "(value)",
      "static" : false,
      "memberOf" : "",
      "isStatic" : false,
      "isConstructor" : false,
      "isPrivate" : false,
      "example" : "",
      "deprecated" : "",
      "since" : "",
      "see" : "",
      "exceptions" : "",
      "requires" : "",
      "params" : [
        {
          "name" : "value",
          "type" : "String",
          "desc" : "The value to decode",
          "isOptional" : false
        }
      ],
      "returns" : [
        {
          "name" : "",
          "type" : "Mixed",
          "desc" : "The decoded value"
        }
      ]
    },
    {
      "name" : "get",
      "type" : "function",
      "desc" : "Returns the current value for a key",
      "sig" : "(name, defaultValue)",
      "static" : false,
      "memberOf" : "",
      "isStatic" : false,
      "isConstructor" : false,
      "isPrivate" : false,
      "example" : "",
      "deprecated" : "",
      "since" : "",
      "see" : "",
      "exceptions" : "",
      "requires" : "",
      "params" : [
        {
          "name" : "name",
          "type" : "String",
          "desc" : "The key name",
          "isOptional" : false
        },
        {
          "name" : "defaultValue",
          "type" : "Mixed",
          "desc" : "A default value to return if the key's value is not found",
          "isOptional" : false
        }
      ],
      "returns" : [
        {
          "name" : "",
          "type" : "Mixed",
          "desc" : "The state data"
        }
      ]
    },
    {
      "name" : "set",
      "type" : "function",
      "desc" : "Sets the value for a key",
      "sig" : "(name, value)",
      "static" : false,
      "memberOf" : "",
      "isStatic" : false,
      "isConstructor" : false,
      "isPrivate" : false,
      "example" : "",
      "deprecated" : "",
      "since" : "",
      "see" : "",
      "exceptions" : "",
      "requires" : "",
      "params" : [
        {
          "name" : "name",
          "type" : "String",
          "desc" : "The key name",
          "isOptional" : false
        },
        {
          "name" : "value",
          "type" : "Mixed",
          "desc" : "The value to set",
          "isOptional" : false
        }
      ],
      "returns" : []
    },
    {
      "name" : "encodeValue",
      "type" : "function",
      "desc" : "Encodes a value including type information.  Decode with {@link #decodeValue}.",
      "sig" : "(value)",
      "static" : false,
      "memberOf" : "",
      "isStatic" : false,
      "isConstructor" : false,
      "isPrivate" : false,
      "example" : "",
      "deprecated" : "",
      "since" : "",
      "see" : "",
      "exceptions" : "",
      "requires" : "",
      "params" : [
        {
          "name" : "value",
          "type" : "Mixed",
          "desc" : "The value to encode",
          "isOptional" : false
        }
      ],
      "returns" : [
        {
          "name" : "",
          "type" : "String",
          "desc" : "The encoded value"
        }
      ]
    }
  ],
  "events" : [
    {
      "name" : "statechange",
      "type" : "function",
      "desc" : "Fires when a state change occurs.",
      "sig" : "function (_self, key, value)\n{\n\n}",
      "memberOf" : "",
      "example" : "",
      "deprecated" : "",
      "since" : "",
      "see" : "",
      "params" : [
        {
          "name" : "this",
          "type" : "Provider",
          "desc" : "This state provider",
          "isOptional" : false
        },
        {
          "name" : "key",
          "type" : "String",
          "desc" : "The state key which was changed",
          "isOptional" : false
        },
        {
          "name" : "value",
          "type" : "String",
          "desc" : "The encoded value for the state",
          "isOptional" : false
        }
      ],
      "returns" : []
    }
  ]
}