{
  "name" : "Roo.htmleditor.FilterEmpty",
  "augments" : [],
  "childClasses" : {  },
  "tree_children" : [],
  "tree_parent" : [],
  "desc" : "filter empty elements",
  "isSingleton" : false,
  "isStatic" : false,
  "isBuiltin" : false,
  "isAbstract" : false,
  "isBuilderTop" : false,
  "memberOf" : "FilterEmpty",
  "example" : "",
  "deprecated" : "",
  "since" : "",
  "see" : "",
  "params" : [
    {
      "name" : "config",
      "type" : "Object",
      "desc" : "Configuration options",
      "isOptional" : false
    }
  ],
  "returns" : [],
  "throws" : "",
  "requires" : "",
  "config" : [],
  "methods" : [],
  "events" : []
}